{
  "Sheet1": [
    {
      "العنوان": "التوكيد اللفظي (الاسم)",
      "الوصف": "التوكيد اللفظي يكونُ بإعادةِ المُؤكّدِ بلفظهِ أو بمرادفه في الاسم ",
      "الأمثلة": "الْمُجْتَهِدُ الْمُجْتَهِدُ فَائِزٌ.",
      "الملاحظات": "قد كُرّر الاسم (المجتهدُ) لفظًا والغرض من هذا التكريرهو تأكيد الاسم الأول ومنع احتمال غيره، ونلاحظ أن التوكيد تبع حركة ما قبله(المؤكد)."
    },
    {
      "العنوان": "التوكيد اللفظي (الفعل)",
      "الوصف": "التوكيد اللفظي يكونُ بإعادةِ المُؤكّدِ بلفظهِ أو بمرادفه في الفعل",
      "الأمثلة": "حَضَرَ حَضَرَ الْمُدَرِّسُ.",
      "الملاحظات": "كُررالفعل (حضرَ) لفظًا، والغرض من هذا التكرير تأكيد الفعل الأول ومنع احتمال غيره، وهنا أخذ التوكيد حركة ما قبله (المؤكد)."
    },
    {
      "العنوان": "التوكيد اللفظي (الحرف)",
      "الوصف": "التوكيد اللفظي يكونُ بإعادةِ المُؤكّدِ بلفظهِ أو بمرادفه في الحرف",
      "الأمثلة": "لَا لَا أُظْلِمُ أَحَدًا.",
      "الملاحظات": "تم تكرار الحرف (لا) لفظًا، وذلك تأكيدًا للحرف الأول."
    },
    {
      "العنوان": "التوكيد اللفظي (الجمل الاسمية)",
      "الوصف": "التوكيد اللفظي يكونُ بإعادةِ المُؤكّدِ بلفظهِ أو بمرادفه في الجمل الاسمية",
      "الأمثلة": "الْمَدْرَسَةُ جَمِيلَةٌ الْمَدْرَسَةُ جَمِيلَةٌ.",
      "الملاحظات": "كُررت الجملة الاسمية الثانية لفظًا، تأكيدًا للجملة الاسمية الأولى."
    },
    {
      "العنوان": "التوكيد اللفظي (الجمل الفعلية)",
      "الوصف": "التوكيد اللفظي يكونُ بإعادةِ المُؤكّدِ بلفظهِ أو بمرادفه في الجمل الفعلية",
      "الأمثلة": "اتَّقِ اللَّهَ ثُمَّ اتَّقِ اللَّهَ.",
      "الملاحظات": "كُررت الجملة الفعلية الثانية لفظًا، تأكيدًا للجملة الفعلية الأولى."
    },
    {
      "العنوان": "التوكيد اللفظي (الضمائر)",
      "الوصف": "التوكيد اللفظي يكونُ بإعادةِ المُؤكّدِ بلفظهِ أو بمرادفه في الضمائر",
      "الأمثلة": "قَالَ تَعَالَى: \"اسْكُنْ أَنْتَ وَزَوْجُكَ الْجَنَّةَ\".",
      "الملاحظات": "أُكد الضمير المستتر(أنت)، بالضمير المنفصل (أنت)."
    },
    {
      "العنوان": "التوكيد المعنوي (النّفسِ أو العينِ)",
      "الوصف": "التوكيد المعنوي يكون بذكر إحدى ألفاظ التوكيد المعنوية ومنها النّفسِ أو العينِ، فائدةُ التوكيدِ بالنفس والعينِ رفعُ احتمالِ أن يكون في الكلام مجازٌ أو سهوٌ أو نسيانٌ",
      "الأمثلة": "جَاءَ الْأَمِيرُ نَفْسُهُ.",
      "الملاحظات": "فان قلت \"جاء الأميرُ\" فربما يتوهم السامع أن اسناد المجيء إليه، هو على سبيل التجوّز أو النسيان أو السهو، فتؤكده بذكر النفس أو العين، رفعاً لهذا الاحتمال"
    },
    {
      "العنوان": "التوكيد المعنوي (كلٍّ وجميعٍ وعامَّةٍ )",
      "الوصف": "التوكيد المعنوي يكون بذكر إحدى ألفاظ التوكيد المعنوية ومنها: كلٍّ وجميعٍ وعامَّةٍ، وفائدةُ التوكيد بكلٍّ وجميعٍ وعامَّةٍ الدلالةُ على الاحاطة والشُّمول",
      "الأمثلة": "قَرَأْتُ الْكِتَابَ كُلَّهُ.",
      "الملاحظات": "تستعمل ألفاظ (كل، جميع ، عامة) لتوكيد الشمول.\n\n"
    },
    {
      "العنوان": "التوكيد المعنوي (كِلا وكِلتا )",
      "الوصف": "التوكيد المعنوي يكون بذكر إحدى ألفاظ التوكيد المعنوية ومنها: كِلا وكِلتا، وفائدةُ التوكيد بكِلا وكِلتا اثباتُ الحُكم للاثنين المُؤكّدينِ معاً.",
      "الأمثلة": "سَقَطَ الْمُلَاكِمَانِ كِلَاهُمَا.",
      "الملاحظات": "تستعمل(كلا وكلتا) لتوكيد المثنى.\n"
    }
  ],
  "Sheet2": [
    {
      "Unnamed: 0": "",
      "التوكيد وأنواعه": "",
      "Unnamed: 2": "",
      "Unnamed: 3": "",
      "Unnamed: 4": "",
      "Unnamed: 5": ""
    },
    {
      "Unnamed: 0": "",
      "التوكيد وأنواعه": "نوع التوكيد",
      "Unnamed: 2": "تعريفه",
      "Unnamed: 3": "المؤكَّد",
      "Unnamed: 4": "المثال ",
      "Unnamed: 5": "التوضيح"
    },
    {
      "Unnamed: 0": "",
      "التوكيد وأنواعه": "التوكيد اللفظي",
      "Unnamed: 2": "هو تكرار اللفظ نفسه كما هو، سواء كان اسمًا أو فعلاً أو حرفًا أو جملة",
      "Unnamed: 3": "اسم أو فعل أو حرف أو جملة",
      "Unnamed: 4": "جاءَ مُحمَّدٌ مُحمَّدٌ.",
      "Unnamed: 5": "كرّر الاسم \"محمد\" لتأكيد حضوره بنفسه، دون شك."
    },
    {
      "Unnamed: 0": "",
      "التوكيد وأنواعه": "",
      "Unnamed: 2": "",
      "Unnamed: 3": "",
      "Unnamed: 4": "كَتَبَ كَتَبَ مُحمَّدٌ الدَّرْسَ.",
      "Unnamed: 5": "تكرار الفعل \"كتب\" توكيد فعلي لما قام به محمد."
    },
    {
      "Unnamed: 0": "",
      "التوكيد وأنواعه": "",
      "Unnamed: 2": "",
      "Unnamed: 3": "",
      "Unnamed: 4": "لا لا تُهمِلْ صَلاتَك.",
      "Unnamed: 5": "تكرار \"لا\" لتأكيد النهي بشدة."
    },
    {
      "Unnamed: 0": "",
      "التوكيد وأنواعه": "",
      "Unnamed: 2": "",
      "Unnamed: 3": "",
      "Unnamed: 4": "إنَّ اللهَ غفورٌ إنَّ اللهَ غفورٌ. (توكيد جملة)",
      "Unnamed: 5": "توكيد الجملة كاملة لإزالة الشك وتثبيت المعنى."
    },
    {
      "Unnamed: 0": "",
      "التوكيد وأنواعه": "التوكيد المعنوي",
      "Unnamed: 2": "هو تأكيد الاسم بألفاظ مخصوصة (نفس، عين، كل، جميع، كلا، كلتا) بحسب المعنى المقصود لإزالة اللبس أو التوهّم",
      "Unnamed: 3": "اسم ظاهر",
      "Unnamed: 4": "جاءَ مُحمَّدٌ نفسُهُ.",
      "Unnamed: 5": "\"نفسه\" تؤكد أن الآتي هو محمد نفسه، وليست رسوله أو نائبه."
    },
    {
      "Unnamed: 0": "",
      "التوكيد وأنواعه": "",
      "Unnamed: 2": "",
      "Unnamed: 3": "",
      "Unnamed: 4": "مررتُ بالمهندسينَ كِلَيهِما.",
      "Unnamed: 5": "\"كليهما\" تؤكد أن المتكلم مرّ بكلا المهندسين معًا، وليس بواحد فقط."
    },
    {
      "Unnamed: 0": "",
      "التوكيد وأنواعه": "",
      "Unnamed: 2": "",
      "Unnamed: 3": "",
      "Unnamed: 4": "نجَحَ الطُلّابُ جميعُهم.",
      "Unnamed: 5": "\"جميعهم\" تؤكد شمول النجاح لكل الطلاب، لا لبعضهم فقط."
    },
    {
      "Unnamed: 0": "",
      "التوكيد وأنواعه": "",
      "Unnamed: 2": "",
      "Unnamed: 3": "",
      "Unnamed: 4": "حضَرَ الجنودُ كلُّهم.",
      "Unnamed: 5": "\"كلهم\" تؤكد أن جميع الجنود حضروا بلا استثناء."
    },
    {
      "Unnamed: 0": "",
      "التوكيد وأنواعه": "",
      "Unnamed: 2": "",
      "Unnamed: 3": "",
      "Unnamed: 4": "رأيتُ الطالبتَينِ كِلْتاهُما.",
      "Unnamed: 5": "\"كلتاهما\" تؤكد أن الرؤية شملت الطالبتين دون نقص."
    },
    {
      "Unnamed: 0": "",
      "التوكيد وأنواعه": "",
      "Unnamed: 2": "",
      "Unnamed: 3": "",
      "Unnamed: 4": "زارني الوزيرُ عينُهُ.",
      "Unnamed: 5": "\"عينه\" تؤكد أن الذي زار هو الوزير بعينه، وليس مندوبًا عنه."
    }
  ]
}