[
  {
    "الملاحظات": "",
    "الإعراب": "كوكبًا : تمييز منصوب و علامة نصبه تنوين الفتح .",
    "الوصف": "فالعدد مبهم و (كوكبًا) التمييز الذي أزال الإبهام",
    "الأمثلة": "قال تعالى : {  إِذ قالَ يوسُفُ لِأَبيهِ يا أَبَتِ إِنّي رَأَيتُ أَحَدَ عَشَرَ كَوكَبًا}[ يوسف:  ٤ ]",
    "العنوان": "الأعداد"
  },
  {
    "الملاحظات": "",
    "الإعراب": "عنبًا : تمييز منصوب و علامة نصبه تنوين الفتح .",
    "الوصف": "كلمة الرطل تدل على مقدار أو وزن و (عنبًا) جاء ليزيل الإبهام .",
    "الأمثلة": "اشْتَرَيْتُ رِطْلًا عِنَبًا",
    "العنوان": "المقادير : أي مقدار منضبط (محدد) من وزن أو كيل أو مساحة ."
  },
  {
    "الملاحظات": "",
    "الإعراب": "خيرًا: تمييز منصوب و علامة نصبه تنوين الفتح .",
    "الوصف": "كلمة ذرة يدل على أشباه المقادير أو وزن و (خيرًا) جاء ليزيل الإبهام .",
    "الأمثلة": "قال تعالى :{  فَمَن يَعمَل مِثقالَ ذَرَّةٍ خَيرًا يَرَهُ }[ الزلزلة:  ٧ ]",
    "العنوان": "أشباه المقادير :يُقصد ذلك ما دلَّ على مقدار غير منضبط تحديدًا و بدقة , وزنًا أو كيلًا أو مساحة , و لم يتعارف الناس على استعماله كمقدار معين "
  },
  {
    "الملاحظات": "",
    "الإعراب": "قطنًا : تمييز منصوب و علامة نصبه تنوين الفتح.",
    "الوصف": "أزالت كلمة ( قطنًا) الغموض عن كلمة ( قميصًا) التي تدل على فرع تمييز , فالقميص فرع القطن , فوجود كلمة (قطنًا) نفى أن يكون نوع القميص حريرًا أو صوفًا أو غير ذلك .",
    "الأمثلة": "لَبِسْتُ قَمِيصًا قُطْنًا",
    "العنوان": "فرعًا للتمييز ( ما كان فرعًا للنوع)"
  }
]