[
  {
    "العنوان": "تأثيره على الكلمة ( من حيث البناء والإعراب  )",
    "الوصف": "لا يؤثر حرف الشين على من حيث البناء والاعراب إلا أنه يكون موجود من ضمن البناء اللغوي للكلمة",
    "الأمثلة": "خَدَشَ الحائطَ\nيَنْقُشُ الخَشَبَ",
    "الملاحظات": ""
  },
  {
    "العنوان": "الموقع الإعرابي للحرف ",
    "الوصف": "لا يؤثر حرف الشين على الكلمة من حيث الموقع الإعرابي إلا أنه يكون موجود من ضمن البناء اللغوي للكلمة",
    "الأمثلة": "مَرَرتُ بالجَيْشِ\nرأيتُ الخَقَّاشَ\nالوَحْشُ في الخزانةِ",
    "الملاحظات": ""
  },
  {
    "العنوان": "دور الحرف  النحوي  في الكلمة من حيث  (التأنيث - التذكير ) ",
    "الوصف": "لا يؤثر حرف الشين وحده في التذكير والتأنيث، لكنه يظهر في بعض الصيغ المرتبطة.",
    "الأمثلة": "شمس\nشاهر\nشجرة\nمشمش",
    "الملاحظات": ""
  },
  {
    "العنوان": "دور الحرف  النحوي  في الكلمة من حيث (  الجمع - التثنية  ) ",
    "الوصف": "يظهر الشين في بعض صيغ الجمع والتثنية، لكنها ليست علامة مميزة لهما ولكنه قد يكون من ضمن السياق",
    "الأمثلة": "أشجار \\\\ شجرتين\nوُحُوش \nأشْواك",
    "الملاحظات": ""
  },
  {
    "العنوان": "دور الحرف  النحوي  في الكلمة من حيث  ( االلزوم - التّعدي     )  ",
    "الوصف": "الحرف الشين ليس له دور نحوي مباشر في تحديد اللّزوم والتعدّي ولكنه قد يكون من ضمن الفعل اللازم أو المتعدي",
    "الأمثلة": "عَشِقَ الغلامُ\n\nطَرَقَ البابَ",
    "الملاحظات": ""
  },
  {
    "العنوان": "دور الحرف  النحوي  في الكلمة  من حيث ( النّسب - التّصغير )  ",
    "الوصف": "لا دور له في النسب والتصغير  ولكنه قد يكون من أصل الكلمة التي تم تصغيرها أو نسبها",
    "الأمثلة": "*",
    "الملاحظات": ""
  },
  {
    "العنوان": "دور الحرف  النحوي  في الكلمة ( المصدر الميمي  - صيغ المبالغة  )  ",
    "الوصف": "لا دور له في المصدر الميمي وصيغ المبالغة  ولكنه قد يكون من أصل الكلمة التي أخذ منها المصدر",
    "الأمثلة": "*",
    "الملاحظات": ""
  },
  {
    "العنوان": "دور الحرف  النحوي  في الكلمة من حيث (  اسم الفاعل - اسم المفعول )  ",
    "الوصف": "لا دور له في اسم الفاعل والمفعول غير ورودها حرف من جذر بعض المشتقات ",
    "الأمثلة": "*",
    "الملاحظات": ""
  },
  {
    "العنوان": "دور الحرف  النحوي  في الكلمة من حيث ( الزمان - المكان )  ",
    "الوصف": "الحرف الشين لا يغيّر قاعدة اشتقاق اسم الزمان والمكان، لكنه قد يكون جزءًا من الجذر الفعلي الذي يُشتق منه الاسم",
    "الأمثلة": "*",
    "الملاحظات": ""
  }
]