[
  {
    "الأمثلة": "حَجَرٌ: حَجَرِيَّةٌ\nعَالَمٌ: عَالَمِيَّةٌ\nنَفْسٌ: نَفْسِيَّةٌ",
    "الوصف": "يُصاغ المصدر الصناعي من الاسم الجامد",
    "العنوان": "1- الأسماء الجامدة"
  },
  {
    "الأمثلة": "كَيْفَ: كَيْفِيَّةٌ\nكَمْ: كَمِّيَّةٌ\nحَيْثُ: حَيْثِيَّةٌ",
    "الوصف": "يُصاغ المصدر الصناعي من الاسم المبني",
    "العنوان": "2- الأسماء المبنيّة"
  },
  {
    "الأمثلة": "اثنَيْنِ: اثنَيْنِيَّةٌ، لُصُوصٌ: لُصُوصِيَّةٌ، صِبْيَانٌ: صِبْيَانِيَّةٌ",
    "الوصف": "يُصاغ المصدر الصناعي من المثنى والجمع",
    "العنوان": "3- المثنى والجمع"
  },
  {
    "الأمثلة": "رَأْسُ مَالٍ: رَأْسْمَالِيَّةٌ، مَا هُوَ: مَاهِيَّةٌ",
    "الوصف": "يُصاغ المصدر الصناعي من الأسماء المركبة",
    "العنوان": "4- الأسماء المركبة"
  },
  {
    "الأمثلة": "فِرْعَوْنُ: فِرْعَوْنِيَّةٌ، قَيْصَرُ: قَيْصَرِيَّةٌ",
    "الوصف": "يُصاغ المصدر الصناعي من الأسماء الأعجميَّة",
    "العنوان": "5- الأسماء الأعجميَّة"
  },
  {
    "الأمثلة": " اشْتِرَاكٌ = اشْتِرَاكيَّةٌ",
    "الوصف": "يُصاغ المصدر الصناعي من المصادر",
    "العنوان": "6- المصادر"
  },
  {
    "الأمثلة": "جَاهَلٌ = جَاهِلِيَّةٌ \nمَفْهُومٌ = مَفْهُومِيَّةٌ\nأَفْضَلُ = أَفْضَلِيَّةٌ\nكَرِيمٌ = كَرِيمِيَّةٌ",
    "الوصف": "يُصاغ المصدر الصناعي من الأسماء المشتقة",
    "العنوان": "7- الأسماء المشتقة"
  }
]